openstat/__init__.py
openstat/bpl.py
openstat/con.py
openstat/evd.py
openstat/final.py
openstat/lgc.py
openstat/tbl.py
openstat/tools.py
openstat-1.6.dist-info/METADATA
openstat-1.6.dist-info/WHEEL
openstat-1.6.dist-info/top_level.txt
openstat-1.6.dist-info/RECORD
