Metadata-Version: 2.1
Name: openstat
Version: 1.6
Requires-Dist: numpy
Requires-Dist: sympy
Requires-Dist: scipy
Requires-Dist: matplotlib
Requires-Dist: requests
